duh.py
setup.py
duh.egg-info/PKG-INFO
duh.egg-info/SOURCES.txt
duh.egg-info/dependency_links.txt
duh.egg-info/entry_points.txt
duh.egg-info/top_level.txt