Metadata-Version: 1.0
Name: duh
Version: 1.03
Summary: Human and sorted output for du
Home-page: https://github.com/grimborg/duh
Author: Oscar Vilaplana
Author-email: dev@oscarvilaplana.cat
License: http://www.gnu.org/licenses/gpl-2.0.html
Platform: UNKNOWN
